pyhasse.core-0.2.3-py3.9-nspkg.pth
pyhasse/core/__init__.py
pyhasse/core/csv_io.py
pyhasse/core/dot.py
pyhasse/core/hddata.py
pyhasse/core/matrix.py
pyhasse/core/order.py
pyhasse/core/tables.py
pyhasse.core-0.2.3.dist-info/AUTHORS.rst
pyhasse.core-0.2.3.dist-info/LICENSE
pyhasse.core-0.2.3.dist-info/METADATA
pyhasse.core-0.2.3.dist-info/WHEEL
pyhasse.core-0.2.3.dist-info/namespace_packages.txt
pyhasse.core-0.2.3.dist-info/top_level.txt
pyhasse.core-0.2.3.dist-info/RECORD
