Metadata-Version: 2.1
Name: pyhasse.core
Version: 0.2.3
Summary: Basics of partial order aiming at data analysis.
Home-page: https://pyhasse.org
Author: Rainer Bruggemann
Author-email: rainer.bruggemann@pyhasse.org
License: MIT license
Download-URL: https://gitlab.com/pyhasse/core/
Keywords: core
Platform: UNKNOWN
Classifier: Development Status :: 2 - Pre-Alpha
Classifier: Intended Audience :: Developers
Classifier: Intended Audience :: Science/Research
Classifier: Topic :: Scientific/Engineering :: Mathematics
Classifier: License :: OSI Approved :: MIT License
Classifier: Natural Language :: English
Classifier: Programming Language :: Python :: 3.7
Requires-Dist: setuptools
Provides-Extra: testing
Requires-Dist: pytest ; extra == 'testing'
Requires-Dist: pytest-cov ; extra == 'testing'
